{
  "spec_version": 1,
  "asset_id": "torus_ring",
  "asset_type": "static_mesh",
  "license": "CC0-1.0",
  "seed": 6004,
  "description": "Torus ring with subdivision - donut shape",
  "outputs": [
    {
      "kind": "primary",
      "format": "glb",
      "path": "torus_ring.glb"
    }
  ],
  "recipe": {
    "kind": "static_mesh.blender_primitives_v1",
    "params": {
      "base_primitive": "torus",
      "dimensions": [1.0, 1.0, 0.3],
      "modifiers": [
        {
          "type": "subdivision",
          "levels": 1,
          "render_levels": 2
        }
      ],
      "uv_projection": "smart",
      "material_slots": [
        {
          "name": "GoldMetal",
          "base_color": [1.0, 0.843, 0.0, 1.0],
          "metallic": 1.0,
          "roughness": 0.2
        }
      ],
      "export": {
        "apply_modifiers": true,
        "triangulate": true,
        "include_normals": true,
        "include_uvs": true,
        "include_vertex_colors": false,
        "tangents": true
      }
    }
  }
}
